learndb/__init__.py
learndb/database.py
learndb-0.0.1.dist-info/LICENSE
learndb-0.0.1.dist-info/METADATA
learndb-0.0.1.dist-info/WHEEL
learndb-0.0.1.dist-info/top_level.txt
learndb-0.0.1.dist-info/RECORD
